bit24/__init__.py
bit24/_utils.py
bit24/clients/__init__.py
bit24/clients/_abstract.py
bit24/clients/_core.py
bit24/clients/async_client.py
bit24/clients/client.py
bit24/enums.py
bit24/exceptions.py
bit24/types/__init__.py
bit24/types/client.py
bit24/types/responses/__init__.py
bit24/types/responses/assets_history.py
bit24/types/responses/assets_information.py
bit24/types/responses/base.py
bit24/types/responses/cancel_order.py
bit24/types/responses/coin_info.py
bit24/types/responses/create_order.py
bit24/types/responses/deposit_networks.py
bit24/types/responses/markets_info.py
bit24/types/responses/order_book.py
bit24/types/responses/orders_history.py
bit24/types/responses/submit_withdraw.py
bit24/types/responses/withdraw_networks.py
python_bit24-0.1.0.dist-info/LICENSE
python_bit24-0.1.0.dist-info/METADATA
python_bit24-0.1.0.dist-info/WHEEL
python_bit24-0.1.0.dist-info/RECORD
