Metadata-Version: 2.1
Name: python-bit24
Version: 0.1.0
Summary: Unofficial Python SDK for Bit24
License: MIT
Author: AMiWR
Author-email: amiwrpremium@gmail.com
Requires-Python: >=3.10,<4.0
Classifier: License :: OSI Approved :: MIT License
Classifier: Programming Language :: Python :: 3
Classifier: Programming Language :: Python :: 3.10
Classifier: Programming Language :: Python :: 3.11
Classifier: Programming Language :: Python :: 3.12
Requires-Dist: aiohttp (>=3.9.4,<4.0.0)
Requires-Dist: requests (>=2.31.0,<3.0.0)
